setup.py
culturestreak/__init__.py
culturestreak/processor.py
culturestreak.egg-info/PKG-INFO
culturestreak.egg-info/SOURCES.txt
culturestreak.egg-info/dependency_links.txt
culturestreak.egg-info/top_level.txt