Metadata-Version: 1.0
Name: culturestreak
Version: 1.1
Summary: culturestreak
Home-page: UNKNOWN
Author: UNKNOWN
Author-email: UNKNOWN
License: UNKNOWN
Platform: UNKNOWN
